uni_tokenizer-0.1.1.dist-info/METADATA
uni_tokenizer-0.1.1.dist-info/WHEEL
uni_tokenizer-0.1.1.dist-info/licenses/LICENSE
uni_tokenizer/__init__.py
uni_tokenizer/_lib.pyd
uni_tokenizer/_lib.pyi
uni_tokenizer/encoder.py
uni_tokenizer/py.typed
uni_tokenizer/trainer.py
uni_tokenizer-0.1.1.dist-info/RECORD
