Metadata-Version: 2.4
Name: uni-tokenizer
Version: 0.1.1
Requires-Dist: numpy>=1.26
License-File: LICENSE
Summary: Fast BPE tokenizer/trainer with a Rust core and Python bindings
Requires-Python: >=3.11
